__init__.py
auth.py
client.py
config.py
task.py
examples/__init__.py
examples/dev_client.py
examples/simple_client.py
examples/team_switching.py
utils/__init__.py
utils/validators.py
agentds-1.0.0.dist-info/METADATA
agentds-1.0.0.dist-info/WHEEL
agentds-1.0.0.dist-info/top_level.txt
agentds-1.0.0.dist-info/RECORD
