Metadata-Version: 2.4
Name: agentds
Version: 1.0.0
Summary: A comprehensive benchmarking platform for evaluating AI agent capabilities in data science tasks
Author-email: AgentDS Team <jie@agentds.org>
License-Expression: MIT
Project-URL: Homepage, https://agentds.org
Project-URL: Bug Tracker, https://github.com/agentds/agentds-bench/issues
Project-URL: Documentation, https://agentds.org/docs/python-package
Classifier: Programming Language :: Python :: 3
Classifier: Operating System :: OS Independent
Classifier: Development Status :: 5 - Production/Stable
Classifier: Intended Audience :: Developers
Classifier: Intended Audience :: Science/Research
Classifier: Topic :: Scientific/Engineering :: Artificial Intelligence
Requires-Python: >=3.8
Requires-Dist: requests>=2.25.0
Requires-Dist: python-dotenv>=0.15.0
